flask_restful_hal/__init__.py
flask_restful_hal/_version.py
flask_restful_hal/api.py
flask_restful_hal/representation.py
flask_restful_hal/resource.py
flask_restful_hal-0.2.6.dist-info/LICENSE
flask_restful_hal-0.2.6.dist-info/METADATA
flask_restful_hal-0.2.6.dist-info/WHEEL
flask_restful_hal-0.2.6.dist-info/top_level.txt
flask_restful_hal-0.2.6.dist-info/RECORD
