Metadata-Version: 2.1
Name: flask-restful-hal
Version: 0.2.6
Summary: HAL extension for Flask-RESTful
Home-page: https://github.com/sciapp/flask-restful-hal
Author: Ingo Heimbach
Author-email: i.heimbach@fz-juelich.de
License: MIT
Keywords: Flask,RESTful,HAL
Platform: UNKNOWN
Classifier: Development Status :: 4 - Beta
Classifier: Environment :: Web Environment
Classifier: Framework :: Flask
Classifier: Intended Audience :: Developers
Classifier: License :: OSI Approved :: MIT License
Classifier: Programming Language :: Python :: 2.7
Classifier: Programming Language :: Python :: 3.3
Classifier: Programming Language :: Python :: 3.4
Classifier: Programming Language :: Python :: 3.5
Classifier: Programming Language :: Python :: 3.6
Classifier: Topic :: Internet :: WWW/HTTP
Requires-Python: >=2.7, !=3.0.*, !=3.1.*, !=3.2.*, <4
Requires-Dist: Flask
Requires-Dist: Flask-RESTful
Requires-Dist: future
